MeanStars/EEM_dwarf_UBVIJHK_colors_Teff.txt
MeanStars/MeanStars.py
MeanStars/__init__.py
meanstars-3.6.0.dist-info/licenses/LICENSE
meanstars-3.6.0.dist-info/METADATA
meanstars-3.6.0.dist-info/WHEEL
meanstars-3.6.0.dist-info/top_level.txt
meanstars-3.6.0.dist-info/RECORD
