Metadata-Version: 2.4
Name: MeanStars
Version: 3.6.0
Summary: Automated property interpolation and color calculations for main sequence stars
Author-email: Dmitry Savransky <ds264@cornell.edu>
Maintainer-email: Dmitry Savransky <ds264@cornell.edu>
License-Expression: BSD-3-Clause
Project-URL: Homepage, https://github.com/dsavransky/MeanStars
Project-URL: Repository, https://github.com/dsavransky/MeanStars
Project-URL: Issues, https://github.com/dsavransky/MeanStars/issues
Classifier: Development Status :: 5 - Production/Stable
Classifier: Intended Audience :: Education
Classifier: Intended Audience :: Science/Research
Classifier: Topic :: Scientific/Engineering :: Mathematics
Classifier: Topic :: Scientific/Engineering :: Physics
Classifier: Programming Language :: Python :: 3
Classifier: Programming Language :: Python :: 3.10
Classifier: Programming Language :: Python :: 3.11
Classifier: Programming Language :: Python :: 3.12
Classifier: Programming Language :: Python :: 3.13
Requires-Python: >=3.10
License-File: LICENSE
Requires-Dist: numpy
Requires-Dist: scipy
Requires-Dist: astropy
Dynamic: license-file
